slice_to_offset_range.py
slice_to_offset_range-0.1.0a1.dist-info/licenses/LICENSE
slice_to_offset_range-0.1.0a1.dist-info/METADATA
slice_to_offset_range-0.1.0a1.dist-info/WHEEL
slice_to_offset_range-0.1.0a1.dist-info/top_level.txt
slice_to_offset_range-0.1.0a1.dist-info/RECORD
