Metadata-Version: 2.4
Name: slice-to-offset-range
Version: 0.1.0a1
Summary: A utility function that converts Python slice objects to explicit `(start_offset, stop_offset, step)` offset ranges given a sequence length.
Author-email: Jifeng Wu <jifengwu2k@gmail.com>
License-Expression: MIT
Project-URL: Homepage, https://github.com/jifengwu2k/slice-to-offset-range
Project-URL: Bug Tracker, https://github.com/jifengwu2k/slice-to-offset-range/issues
Classifier: Programming Language :: Python :: 2
Classifier: Programming Language :: Python :: 3
Classifier: Operating System :: OS Independent
Requires-Python: >=2
License-File: LICENSE
Requires-Dist: canonicalize-range
Dynamic: license-file
